labmath/__init__.py
labmath/labmath.py
labmath-2.1.3.dist-info/LICENSE
labmath-2.1.3.dist-info/METADATA
labmath-2.1.3.dist-info/WHEEL
labmath-2.1.3.dist-info/top_level.txt
labmath-2.1.3.dist-info/RECORD
