Metadata-Version: 2.1
Name: labmath
Version: 2.1.3
Summary: Module for basic math in the general vicinity of computational number theory
Home-page: https://pypi.org/manage/project/labmath
Author: lucasbrown.cit
Author-email: lucasbrown.cit@gmail.com
License: UNKNOWN
Keywords: math mathematics computational number theory integer factoring factorization primes prime numbers semiprime almost prime almost-prime legendre symbol jacobi symbol kronecker symbol elliptic curve method bpsw miller rabin quadratic frobenius prp sprp lprp slprp xslprp primality testing linear recurrences lucas sequences modular square root generalized Pell equations divisor counting function euler's totient function mobius function möbius function continued fractions partitions stormer'
Platform: UNKNOWN
Classifier: Programming Language :: Python :: 3
Classifier: License :: OSI Approved :: MIT License
Classifier: Operating System :: OS Independent
Classifier: Development Status :: 5 - Production/Stable
Classifier: Environment :: Console
Classifier: Intended Audience :: Education
Classifier: Intended Audience :: Science/Research
Classifier: Topic :: Scientific/Engineering
Classifier: Topic :: Scientific/Engineering :: Mathematics
Classifier: Topic :: Software Development :: Libraries
Classifier: Topic :: Software Development :: Libraries :: Python Modules
Requires-Python: >=3.6
License-File: LICENSE
